topsis_tushargarg_102303674/__init__.py
topsis_tushargarg_102303674/topsis.py
topsis_tushargarg_102303674-0.1.1.dist-info/METADATA
topsis_tushargarg_102303674-0.1.1.dist-info/WHEEL
topsis_tushargarg_102303674-0.1.1.dist-info/entry_points.txt
topsis_tushargarg_102303674-0.1.1.dist-info/top_level.txt
topsis_tushargarg_102303674-0.1.1.dist-info/RECORD
