Metadata-Version: 2.4
Name: Topsis-Tushargarg-102303674
Version: 0.1.1
Summary: A Python package for TOPSIS multi-criteria decision making
Author: Tushar
Author-email: tgarg3_be23@thapar.edu
Requires-Python: >=3.7
Requires-Dist: pandas
Requires-Dist: numpy
Dynamic: author
Dynamic: author-email
Dynamic: description
Dynamic: description-content-type
Dynamic: requires-dist
Dynamic: requires-python
Dynamic: summary
